{
	"name": "Ragnarok",
	"type": "dark",
	"semanticHighlighting": false,

	"colors": {
		"contrastActiveBorder": null,
		"contrastBorder": "#333300",

    "focusBorder": "#333300",
    "foreground": "#d6deeb",
    "widget.shadow": "#191900",
    "selection.background": "#4373c2",
		"descriptionForeground": null,
    "errorForeground": "#EF5350",
		"icon.foreground": null,
		"sash.hoverBorder": null,

		"window.activeBorder": null,
		"window.inactiveBorder": null,
		
		"textBlockQuote.background": null,
		"textBlockQuote.border": null,
		"textLink.activeForeground": null,
		"textLink.foreground": null,
		"textPreformat.foreground": null,
		"textSeparator.foreground": null,

		"toolbar.hoverBackground": null,
		"toolbar.hoverOutline": null,
		"toolbar.activeBackground": null,

		"button.background": "#e6e600cc",
    "button.foreground": "#000000",
		"button.border": null,
    "button.hoverBackground": "#e6e600F2",
		"button.secondaryBackground": null,
		"button.secondaryForeground": null,
		"button.secondaryHoverBackground": null,
		"checkbox.background": null,
		"checkbox.foreground": null,
		"checkbox.border": "#808000",


    "dropdown.background": "#1b1b1b",
		"dropdown.listBackground": null,
    "dropdown.border": "#808000",
    "dropdown.foreground": "#ffffffcc",
		
    "input.background": "#171717",
    "input.border": "#808000",
    "input.foreground": "#ffffffcc",
    "input.placeholderForeground": "#808080",

		"inputOption.activeBackground": null,
		"inputOption.activeBorder": "#ff0000",
		"inputOption.activeForeground": "#ff0000",



    "inputValidation.errorBackground": "#AB0300F2",
		"inputValidation.errorForeground": null,
    "inputValidation.errorBorder": "#EF5350",
    "inputValidation.infoBackground": "#00589EF2",
		"inputValidation.infoForeground": null,
    "inputValidation.infoBorder": "#64B5F6",
    "inputValidation.warningBackground": "#675700F2",
		"inputValidation.warningForeground": null,
    "inputValidation.warningBorder": "#FFCA28",

    "scrollbar.shadow": "#191900",
    "scrollbarSlider.activeBackground": "#66660080",
    "scrollbarSlider.background": "#66660080",
    "scrollbarSlider.hoverBackground": "#66660080",
		
    "badge.background": "#b3b300E6",
    "badge.foreground": "#000000",




    "progressBar.background": "#b3b300E6",

		"list.activeSelectionBackground": "#9999008c",
    "list.activeSelectionForeground": "#ffffff",


    "list.dropBackground": "#333300",
    "list.focusBackground": "#333300",
    "list.focusForeground": "#ffffff",
    "list.highlightForeground": "#ffffff",
		"list.focusHighlightForeground": null,
		"list.focusOutline": null,
    "list.hoverBackground": "#171717",
    "list.hoverForeground": "#ffffff",
    "list.inactiveSelectionBackground": "#333300",
    "list.inactiveSelectionForeground": "#FFFFFF80",
		"list.inactiveFocusBackground": null,
		"list.inactiveFocusOutline": null,

		"list.invalidItemForeground": "#975f94",
		"list.errorForeground": null,
		"list.warningForeground": null,
		"listFilterWidget.background": null,
		"listFilterWidget.outline": null,
		"listFilterWidget.noMatchesOutline": null,
		"list.filterMatchBackground": null,
		"list.filterMatchBorder": null,
		"list.deemphasizedForeground": null,

		"tree.indentGuidesStroke": null,
		"tree.tableColumnsBorder": null,
		

		
    "activityBar.background": "#1b1b1b",
    "activityBar.dropBorder": null,
    "activityBar.foreground": "#b3b300",
		"activityBar.inactiveForeground": null,
    "activityBar.border": "#333300",

    "activityBarBadge.background": "#b3b300E6",
    "activityBarBadge.foreground": "#000000",

		"activityBar.activeBorder": null,
		"activityBar.activeBackground": null,
		"activityBar.activeFocusBorder": null,


		
    "sideBar.background": "#171717",
    "sideBar.foreground": "#B3B3B3",
    "sideBar.border": "#333300",
		"sideBar.dropBackground": null,
    "sideBarTitle.foreground": "#999999",
    "sideBarSectionHeader.background": "#1a1a1a",
    "sideBarSectionHeader.foreground": "#999900",
		"sideBarSectionHeader.border": null,

		"minimap.findMatchHighlight": "#ffff0099",
		"minimap.selectionHighlight": "#5478e4A6",
		"minimap.errorHighlight": "#FF0000cc",
		"minimap.warningHighlight": null,
		"minimap.background": null,
		"minimapSlider.background": "#2e4a9e40",
		"minimapSlider.hoverBackground": "#2e4a9e40",
		"minimapSlider.activeBackground": "#2e4a9e40",
		"minimapGutter.addedBackground": null,
		"minimapGutter.modifiedBackground": null,
		"minimapGutter.deletedBackground": null,


    "breadcrumb.foreground": "#7eaef1",
    "breadcrumb.focusForeground": "#ffffff",
    "breadcrumb.activeSelectionForeground": "#FFFFFF",
    "breadcrumbPicker.background": "#1b1b1b",
	


    "editorGroup.emptyBackground": "#333300",
    "editorGroup.border": "#333300",
    "editorGroup.dropBackground": "#66660073",
		"editorGroup.focusedEmptyBorder": null,

    "editorGroupHeader.noTabsBackground": "#171717",
    "editorGroupHeader.tabsBackground": "#171717",
    "editorGroupHeader.tabsBorder": "#333300",
		"editorGroupHeader.border": null,

		
    "tab.activeBackground": "#333300",
		"tab.unfocusedActiveBackground": null,
    "tab.activeForeground": "#FFFFFFD9",
    "tab.border": "#333300",
    "tab.activeBorder": "#808000",
		"tab.unfocusedActiveBorder": "#808000",
		"tab.activeBorderTop": null,
		"tab.unfocusedActiveBorderTop": null,
		"tab.lastPinnedBorder": "#808000",
    "tab.inactiveBackground": "#1b1b1b",
		"tab.unfocusedInactiveBackground": null,
    "tab.inactiveForeground": "#999999",
    "tab.unfocusedActiveForeground": "#FFFFFFBF",
    "tab.unfocusedInactiveForeground": "#999999BF",
		"tab.hoverBackground": null,
		"tab.hoverBorder": null,
		"tab.unfocusedHoverBorder": null,
		"tab.activeModifiedBorder": null,
		"tab.inactiveModifiedBorder": null,
		"tab.hoverForeground": null,
		"tab.unfocusedActiveModifiedBorder": null,
		"tab.unfocusedHoverBackground": null,
		"tab.unfocusedHoverForeground": null,
		"tab.unfocusedInactiveModifiedBorder": null,
		
		"editorPane.background": null,

		
    "editor.background": "#131313",
    "editor.foreground": "#C6CFE2",
    "editorLineNumber.foreground": "#595959",
    "editorLineNumber.activeForeground": "#BFBFBF",

    "editorCursor.foreground": "#cccc00",
	
    "editor.selectionBackground": "#1a2a5aCC",
		"editor.selectionForeground": null,

    "editor.selectionHighlightBackground": "#5478e479",
		
    "editor.inactiveSelectionBackground": "#4c4c005a",
		"editor.selectionHighlightBorder": null,

    "editor.wordHighlightBackground": null,
		"editor.wordHighlightBorder": null,
		"editor.wordHighlightStrongBackground": "#e2a2f433",
    "editor.findMatchBackground": "#5478e479",
    "editor.findMatchHighlightBackground": "#5478e48C",
    "editor.findRangeHighlightBackground": null,
		"editor.findMatchBorder": null,
		"editor.findMatchHighlightBorder": null,
		"editor.findRangeHighlightBorder": null,
    "editor.hoverHighlightBackground": "#4c4c007A",
    "editor.lineHighlightBackground": "#1F1F00",
    "editor.lineHighlightBorder": null,
    "editorLink.activeForeground": null,
    "editor.rangeHighlightBackground": "#5478e45a",
		"editor.rangeHighlightBorder": null,
    "editorWhitespace.foreground": null,
    "editorIndentGuide.background": "#4169e152",
    "editorIndentGuide.activeBackground": "#6787e7A6",

    "editorRuler.foreground": "#5e81ce52",
    "editorCodeLens.foreground": "#5e82ceb4",

		"editorLightBulb.foreground": null,
		"editorLightBulbAutoFix.foreground": null,

		"searchEditor.findMatchBackground": null,
		"searchEditor.findMatchBorder": null,
		"searchEditor.textInputBorder": null,


		
    "editorBracketMatch.background": "#131f434d",
    "editorBracketMatch.border": null,

		"editor.foldBackground": null,

		"editorOverviewRuler.background": null,
		"editorOverviewRuler.border": null,
		"editorOverviewRuler.findMatchForeground": null,
		"editorOverviewRuler.rangeHighlightForeground": null,
		"editorOverviewRuler.selectionHighlightForeground": null,
		"editorOverviewRuler.wordHighlightForeground": null,
		"editorOverviewRuler.wordHighlightStrongForeground": null,
		"editorOverviewRuler.modifiedForeground": null,
		"editorOverviewRuler.addedForeground": null,
		"editorOverviewRuler.deletedForeground": null,
		"editorOverviewRuler.infoForeground": null,
		"editorOverviewRuler.bracketMatchForeground": null,
		"editorOverviewRuler.errorForeground": null,
		"editorOverviewRuler.warningForeground": null,
    "editorOverviewRuler.currentContentForeground": "#7e57c2",
    "editorOverviewRuler.incomingContentForeground": "#7e57c2",
    "editorOverviewRuler.commonContentForeground": "#7e57c2",
		
    "editorError.foreground": "#EF5350",
    "editorError.border": null,
		
    "editorWarning.foreground": "#b39554",
    "editorWarning.border": null,
		"editorWarning.background": null,

		"editorInfo.background": null,
		"editorInfo.border": null,
		"editorInfo.foreground": null,

		"editorHint.border": null,
		"editorHint.foreground": null,

		"problemsErrorIcon.foreground": null,
		"problemsWarningIcon.foreground": null,
		"problemsInfoIcon.foreground": null,

		"editorUnnecessaryCode.border": null,
		"editorUnnecessaryCode.opacity": null,
		
    "editorGutter.background": "#171717",

    "editorGutter.modifiedBackground": "#e2b93d",
    "editorGutter.addedBackground": "#9CCC65",
    "editorGutter.deletedBackground": "#EF5350",
		"editorGutter.commentRangeForeground": null,
		"editorGutter.foldingControlForeground": null,
		
    "diffEditor.insertedTextBackground": "#99b76d23",
    "diffEditor.insertedTextBorder": "#c5e47833",
    "diffEditor.removedTextBackground": "#ef535033",
    "diffEditor.removedTextBorder": "#ef53504d",

		"editorWidget.foreground": null,
    "editorWidget.background": "#191900",
    "editorWidget.border": "#666600",
		"editorWidget.resizeBorder": "#666600",

		
    "editorSuggestWidget.background": "#191900",
    "editorSuggestWidget.border": "#808000",
    "editorSuggestWidget.foreground": "#d6deeb",
    "editorSuggestWidget.highlightForeground": "#ffffff",
		"editorSuggestWidget.selectedBackground": "#666600",
		"editorSuggestWidget.focusHighlightForeground": null,
		"editorSuggestWidget.selectedForeground": null,




		"editorHoverWidget.foreground": "#d6deeb",
    "editorHoverWidget.background": "#171717",
    "editorHoverWidget.border": "#808000",
		"editorHoverWidget.statusBarBackground": null,

		"editorGhostText.border": null,
		"editorGhostText.foreground": null,
		

    "debugExceptionWidget.background": "#333300",
    "debugExceptionWidget.border": "#5f7e97",
    "editorMarkerNavigation.background": "#0b2942",
    "editorMarkerNavigationError.background": "#EF5350",
    "editorMarkerNavigationWarning.background": "#FFCA28",

    "peekView.border": "#5f7e97",
    "peekViewEditor.background": "#333300",
    "peekViewEditor.matchHighlightBackground": "#7e57c25a",
    "peekViewResult.background": "#333300",
    "peekViewResult.fileForeground": "#5f7e97",
    "peekViewResult.lineForeground": "#5f7e97",
    "peekViewResult.matchHighlightBackground": "#ffffffcc",
    "peekViewResult.selectionBackground": "#2E3250",
    "peekViewResult.selectionForeground": "#5f7e97",
    "peekViewTitle.background": "#333300",
    "peekViewTitleDescription.foreground": "#697098",
    "peekViewTitleLabel.foreground": "#5f7e97",
    "merge.currentHeaderBackground": "#5f7e97",
    "merge.currentContentBackground": null,
    "merge.incomingHeaderBackground": "#7e57c25a",
    "merge.incomingContentBackground": null,
    "merge.border": null,

		
    "panel.background": null,
    "panel.border": "#333300",
    "panelTitle.activeBorder": "#808000",
    "panelTitle.activeForeground": "#ffffffcc",
    "panelTitle.inactiveForeground": "#d6deeb80",
		"panelInput.border": null,
		




		
    "statusBar.background": "#0f0f0f",
    "statusBar.foreground": "#999999",
    "statusBar.border": "#333300",
		
    "statusBar.debuggingBackground": "#202431",
    "statusBar.debuggingForeground": null,
    "statusBar.debuggingBorder": "#1F2330",
    "statusBar.noFolderForeground": null,
    "statusBar.noFolderBackground": "#333300",
    "statusBar.noFolderBorder": "#25293A",
		
    "statusBarItem.activeBackground": "#202431",
    "statusBarItem.hoverBackground": "#202431",
    "statusBarItem.prominentBackground": "#202431",
    "statusBarItem.prominentHoverBackground": "#202431",
		
    "titleBar.activeBackground": "#171717",
    "titleBar.activeForeground": "#bebfcc",
    "titleBar.inactiveBackground": "#0f0f0f",
    "titleBar.inactiveForeground": null,
		"titleBar.border": null,

		

		
    "notifications.background": "#191900",
    "notifications.border": "#333300",
    "notificationCenter.border": "#333300",
    "notificationToast.border": "#333300",

    "notifications.foreground": "#ffffffcc",
    "notificationLink.foreground": "#80CBC4",
		
    "extensionButton.prominentForeground": "#000000",
    "extensionButton.prominentBackground": "#e6e600cc",
    "extensionButton.prominentHoverBackground": "#e6e600F2",

    "pickerGroup.foreground": "#d1aaff",
    "pickerGroup.border": "#333300",
		
		"terminal.background": null,
		"terminal.border": null,
		"terminal.foreground": null,
		"terminalCursor.foreground": "#b3b300",
    "terminal.ansiWhite": "#ffffff",
    "terminal.ansiBlack": "#333300",
    "terminal.ansiBlue": "#82AAFF",
    "terminal.ansiCyan": "#21c7a8",
    "terminal.ansiGreen": "#22da6e",
    "terminal.ansiMagenta": "#C792EA",
    "terminal.ansiRed": "#EF5350",
    "terminal.ansiYellow": "#c5e478",
    "terminal.ansiBrightWhite": "#ffffff",
    "terminal.ansiBrightBlack": "#575656",
    "terminal.ansiBrightBlue": "#82AAFF",
    "terminal.ansiBrightCyan": "#7fdbca",
    "terminal.ansiBrightGreen": "#22da6e",
    "terminal.ansiBrightMagenta": "#C792EA",
    "terminal.ansiBrightRed": "#EF5350",
    "terminal.ansiBrightYellow": "#ffeb95",
    "terminal.selectionBackground": "#1b90dd4d",
    "terminalCursor.background": null,

    "textCodeBlock.background": "#4f4f4f",
    "debugToolBar.background": "#4c4c00",

    "welcomePage.buttonBackground": null,
    "welcomePage.buttonHoverBackground": "#333300",
    "walkThrough.embeddedEditorBackground": "#333300",

    "gitDecoration.modifiedResourceForeground": "#a0b4f0",
    "gitDecoration.deletedResourceForeground": "#EF535090",
    "gitDecoration.untrackedResourceForeground": "#c5e478ff",
    "gitDecoration.ignoredResourceForeground": "#395a75",
    "gitDecoration.conflictingResourceForeground": "#ffeb95cc",
		
    "source.elm": "#5f7e97",
    "string.quoted.single.js": "#ffffff",
    "meta.objectliteral.js": "#82AAFF"
		





		
	},
	"tokenColors": [
		{
			"name": "Global settings",
      "settings": {
				"foreground": "#c6cfe2"
      }
		},
		{
			"name": "Comment",
			"scope": [
				"comment",
				"punctuation.definition.comment"
			],
			"settings": {
				"foreground": "#5EA046",
				"fontStyle": ""
			}
		},
		{
			"name": "Numbers",
			"scope": ["constant.numeric", "constant.character.numeric"],
			"settings": {
				"foreground": "#b5ce92",
				"fontStyle": ""
			}
		},
		{
			"name": "Boolean 'true'",
			"scope": [
				"constant.language.boolean.true.js"
			],
			"settings": {
				"foreground": "#41C846",
				"fontStyle": ""
			}
		},
		{
			"name": "Boolean 'false'",
			"scope": [
				"constant.language.boolean.false.js"
			],
			"settings": {
				"foreground": "#EB0000",
				"fontStyle": ""
			}
		},
		{
			"name": "Open / closed brackets [HTML]",
			"scope": [
				"punctuation.definition.tag.begin.html",
				"punctuation.definition.tag.end.html"
			],
			"settings": {
				"foreground": "#808080"
			}
		},
		{
			"name": "HTML tags, CSS class/ID [HTML/CSS/JS]",
			"scope": [
				"entity.other.attribute-name.class.css",
				"entity.other.attribute-name.id.css",
				"entity.name.tag",
        "meta.tag.other.html",
        "meta.tag.other.js",
        "meta.tag.other.tsx",
        "entity.name.tag.tsx",
        "entity.name.tag.js",
        "entity.name.tag",
        "meta.tag.js",
        "meta.tag.tsx",
        "meta.tag.html"
			],
			"settings": {
				"foreground": "#DCC218",
				"fontStyle": ""
			}
		},
		{
			"name": "Tag attribute [HTML]",
			"scope": "entity.other.attribute-name",
			"settings": {
				"fontStyle": "",
				"foreground": "#BB7CDA"
			}
		},
		{
			"name": "String [HTML]",
			"scope": [
				"string.quoted.single.html",
				"string.quoted.double.html",
			],
			"settings": {
				"foreground": "#7EAEF1"
			}
		},
		{
			"name": "Variable [CSS]",
      "scope": [
				"variable.css",
				"variable.argument.css"
			],
      "settings": {
				"foreground": "#38C4CC"
      }
    },
		{
			"name": "root and pseudo classes [CSS]",
			"scope": "entity.other.attribute-name.pseudo-class.css",
			"settings": {
				"foreground": "#DB960D",
				"fontStyle": ""
			}
		},
		{
      "name": "Property name, media property name [CSS]",
      "scope": [
				"support.type.property-name.css",
				"support.type.property-name.media.css",
				"support.constant.media.css"
			],
      "settings": {
        "fontStyle": "",
        "foreground": "#7eaef1"
      }
    },
		{
      "name": "Meta properties, @media, import [CSS]",
      "scope": [
				"meta.property-value.css",
				"keyword.control.at-rule.media.css",
				"keyword.control.at-rule.import.css"
			],
      "settings": {
        "fontStyle": "",
        "foreground": "#bb7cda"
      }
    },
		{
			"name": "url [CSS]",
			"scope": "support.function.url.css",
			"settings": {
				"foreground": "#b5ce92",
				"fontStyle": ""
			}
		},
		{
			"name": "Strings [JS]",
			"scope": [
				"string.quoted.single.js",
				"string.quoted.double.css",
				"string.template.js",
			],
			"settings": {
				"foreground": "#DB960D",
				"fontStyle": ""
			}
		},
		{
			"name": "Variables [JS]",
			"scope": [
				"variable.other.object.property.js",
				"variable.other.constant.js",
			],
			"settings": {
				"foreground": "#38C4CC",
				"fontStyle": ""
			}
		},
		{
			"name": "Variables (other) [JS]",
			"scope": [
				"variable.other.property.js",
				"variable.language.this.js",
				"variable.other.object.js",
			],
			"settings": {
				"foreground": "#94B81E",
				"fontStyle": ""
			}
		},
		{
			"name": "Variable (other - rw) [JS]",
			"scope": [
				"variable.other.readwrite.js",
			],
			"settings": {
				"foreground": "#c6cfe2",
				"fontStyle": ""
			}
		},
		{
			"name": "Storage [JS]",
			"scope": [
				"storage.type.class.js",
				"storage.modifier.js",
				"storage.modifier.async.js",
				"storage.type.function.js",
			],
			"settings": {
				"foreground": "#bb7cda",
				"fontStyle": ""
			}
		},
		{
			"name": "Error [JS]",
			"scope": [
				"support.class.error.js"
			],
			"settings": {
				"foreground": "#CFA5E4",
				"fontStyle": ""
			}
		},
		{
			"name": "Class | Entity [JS]",
			"scope": [
				"entity.name.type.class.js",
				"entity.name.function.js",
				"entity.other.inherited-class.js"
			],
			"settings": {
				"foreground": "#7eaef1",
				"fontStyle": ""
			}
		},
		{
			"name": "Keyword [JS]",
			"scope": [
				"keyword.control.conditional.js",
				"keyword.control.trycatch.js",
				"keyword.operator.new.js",
				"keyword.control.loop.js",
				"keyword.operator.expression.of.js",
				"keyword.control.flow.js",
				"keyword.control.flow.js",
				"keyword.control.switch.js",
				"keyword.control.switch.js",
				"keyword.operator.logical.js"
			],
			"settings": {
				"foreground": "#dcc218",
				"fontStyle": ""
			}
		},
		{
			"name": "[JSON] properties, names and tokens",
			"scope": [
				"string.json.comments",
				"support.type.property-name.json"
			],
			"settings": {
				"foreground": "#7eaef1",
				"fontStyle": ""
			}
		},
		{
			"name": "[JSON] token variables and colors",
			"scope": [
				"string.quoted.double.json",
				"storage.type.js"
			],
			"settings": {
				"foreground": "#bb7cda",
				"fontStyle": ""
			}
		},
		{
			"name": "[JSON] constants (true/false | null)",
			"scope": "constant.language.json.comments",
			"settings": {
				"foreground": "#A68067",
				"fontStyle": ""
			}
		},
		{
			"name": "Headings [MD]",
			"scope": [
				"entity.name.section.markdown",
				"punctuation.definition.heading.markdown",
				"markup.heading.setext.1.markdown",
				"markup.heading.setext.2.markdown"
			],
			"settings": {
				"foreground": "#B8A214",
				"fontStyle": "bold"
			}
		},
		{
			"name": "! and [] string [MD]",
			"scope": [
				"punctuation.definition.string.begin.markdown",
				"punctuation.definition.string.end.markdown"
			],
			"settings": {
				"foreground": "#dcc218",
				"fontStyle": ""
			}
		},
		{
			"name": "Numbered list / bold / link text [MD]",
			"scope": [
				"punctuation.definition.list.begin.markdown",
				"markup.bold.markdown",
			],
			"settings": {
				"foreground": "#7eaef1",
				"fontStyle": "bold"
			}
		},
		{
			"name": "italic [MD]",
			"scope": [
				"markup.italic.markdown"
			],
			"settings": {
				"foreground": "#7eaef1",
				"fontStyle": "italic"
			}
		},
		{
			"name": "quote [MD]",
			"scope": [
				"markup.quote.markdown"
			],
			"settings": {
				"foreground": "#93A5C8",
				"fontStyle": "italic"
			}
		},
		{
			"name": "link and filepath [MD]",
			"scope": [
				"meta.link.inline.markdown",
				"meta.image.inline.markdown"
			],
			"settings": {
				"foreground": "#bb7cda",
				"fontStyle": ""
			}
		},
		{
			"name": "link text [MD]",
			"scope": [
				"string.other.link.title.markdown"
			],
			"settings": {
				"foreground": "#7eaef1",
				"fontStyle": ""
			}
		},
		{
			"name": "fenced off code [MD]",
			"scope": [
				"markup.fenced_code.block.markdown",
				"markup.inline.raw.string.markdown"
			],
			"settings": {
				"foreground": "#A68067",
				"fontStyle": ""
			}
		},
		
	]
}